cloudscraper/__init__.py
cloudscraper/cloudflare.py
cloudscraper/cloudflare_v2.py
cloudscraper/cloudflare_v3.py
cloudscraper/exceptions.py
cloudscraper/help.py
cloudscraper/proxy_manager.py
cloudscraper/stealth.py
cloudscraper/turnstile.py
cloudscraper/captcha/2captcha.py
cloudscraper/captcha/9kw.py
cloudscraper/captcha/__init__.py
cloudscraper/captcha/anticaptcha.py
cloudscraper/captcha/capmonster.py
cloudscraper/captcha/capsolver.py
cloudscraper/captcha/deathbycaptcha.py
cloudscraper/interpreters/__init__.py
cloudscraper/interpreters/chakracore.py
cloudscraper/interpreters/encapsulated.py
cloudscraper/interpreters/js2py.py
cloudscraper/interpreters/js2py_interpreter.py
cloudscraper/interpreters/jsunfuck.py
cloudscraper/interpreters/native.py
cloudscraper/interpreters/nodejs.py
cloudscraper/interpreters/v8.py
cloudscraper/user_agent/__init__.py
cloudscraper/user_agent/browsers.json
cloudscraper_enhanced-3.0.0.dist-info/licenses/LICENSE
cloudscraper_enhanced-3.0.0.dist-info/METADATA
cloudscraper_enhanced-3.0.0.dist-info/WHEEL
cloudscraper_enhanced-3.0.0.dist-info/top_level.txt
cloudscraper_enhanced-3.0.0.dist-info/RECORD
