Metadata-Version: 2.4
Name: cloudscraper-enhanced
Version: 3.0.0
Summary: Enhanced Python module to bypass Cloudflare's anti-bot page with support for v2 challenges, proxy rotation, and stealth mode.
Home-page: https://github.com/venomous/cloudscraper
Author: VeNoMouS, Zied Boughdir
Author-email: VeNoMouS <venom@cloudscraper.io>, Zied Boughdir <ziedboughdir@gmail.com>
Maintainer-email: Zied Boughdir <venom@cloudscraper.io>, Zied Boughdir <ziedboughdir@gmail.com>
License: MIT
Project-URL: Homepage, https://github.com/venomous/cloudscraper
Project-URL: Repository, https://github.com/venomous/cloudscraper.git
Project-URL: Issues, https://github.com/venomous/cloudscraper/issues
Project-URL: Changelog, https://github.com/venomous/cloudscraper/blob/master/CHANGELOG.md
Keywords: cloudflare,scraping,ddos,scrape,webscraper,anti-bot,waf,iuam,bypass,challenge
Classifier: Development Status :: 5 - Production/Stable
Classifier: Intended Audience :: Developers
Classifier: Natural Language :: English
Classifier: License :: OSI Approved :: MIT License
Classifier: Operating System :: OS Independent
Classifier: Programming Language :: Python
Classifier: Programming Language :: Python :: 3
Classifier: Programming Language :: Python :: 3.8
Classifier: Programming Language :: Python :: 3.9
Classifier: Programming Language :: Python :: 3.10
Classifier: Programming Language :: Python :: 3.11
Classifier: Programming Language :: Python :: 3.12
Classifier: Programming Language :: Python :: 3.13
Classifier: Topic :: Internet :: WWW/HTTP
Classifier: Topic :: Software Development :: Libraries :: Application Frameworks
Classifier: Topic :: Software Development :: Libraries :: Python Modules
Requires-Python: >=3.8
License-File: LICENSE
Requires-Dist: requests>=2.31.0
Requires-Dist: requests-toolbelt>=1.0.0
Requires-Dist: pyparsing>=3.1.0
Requires-Dist: pyOpenSSL>=24.0.0
Requires-Dist: pycryptodome>=3.20.0
Requires-Dist: websocket-client>=1.7.0
Requires-Dist: js2py>=0.74
Requires-Dist: brotli>=1.1.0
Requires-Dist: certifi>=2024.2.2
Provides-Extra: dev
Requires-Dist: pytest>=8.0.0; extra == "dev"
Requires-Dist: pytest-cov>=4.0.0; extra == "dev"
Requires-Dist: pytest-xdist>=3.0.0; extra == "dev"
Requires-Dist: pytest-asyncio>=0.23.0; extra == "dev"
Requires-Dist: black>=24.0.0; extra == "dev"
Requires-Dist: isort>=5.13.0; extra == "dev"
Requires-Dist: flake8>=7.0.0; extra == "dev"
Requires-Dist: mypy>=1.8.0; extra == "dev"
Requires-Dist: pre-commit>=3.6.0; extra == "dev"
Provides-Extra: test
Requires-Dist: pytest>=8.0.0; extra == "test"
Requires-Dist: pytest-cov>=4.0.0; extra == "test"
Requires-Dist: pytest-xdist>=3.0.0; extra == "test"
Requires-Dist: pytest-asyncio>=0.23.0; extra == "test"
Requires-Dist: responses>=0.24.0; extra == "test"
Dynamic: author
Dynamic: home-page
Dynamic: license-file
Dynamic: requires-python
